enverus_developer_api/__init__.py
enverus_developer_api-3.2.2.dist-info/LICENSE.md
enverus_developer_api-3.2.2.dist-info/METADATA
enverus_developer_api-3.2.2.dist-info/WHEEL
enverus_developer_api-3.2.2.dist-info/top_level.txt
enverus_developer_api-3.2.2.dist-info/RECORD
