Metadata-Version: 2.1
Name: enverus-developer-api
Version: 3.2.2
Summary: Enverus Developer API Python Client
Home-page: https://github.com/enverus-ea/enverus-developer-api
Author: Direct Access
Author-email: directaccess@enverus.com
License: MIT
Keywords: enverus,drillinginfo,directaccess,oil,gas
Classifier: Development Status :: 5 - Production/Stable
Classifier: Intended Audience :: Developers
Classifier: Intended Audience :: End Users/Desktop
Classifier: License :: OSI Approved :: MIT License
Classifier: Operating System :: OS Independent
Classifier: Programming Language :: Python :: 2
Classifier: Programming Language :: Python :: 3
License-File: LICENSE.md
Requires-Dist: requests (<3,>=2.5.1)
Requires-Dist: unicodecsv (==0.14.1)
Requires-Dist: urllib3 (>=1.26.14)
Provides-Extra: pandas
Requires-Dist: pandas (>=0.24.0) ; extra == 'pandas'
